sockoutlet/__init__.py
sockoutlet/proxy/__init__.py
sockoutlet/proxy/plugins/__init__.py
sockoutlet/proxy/plugins/reverse_proxy.py
sockoutlet/proxy/plugins/sandbox_restapi.py
sockoutlet/proxy/sandbox/__init__.py
sockoutlet/proxy/sandbox/manager.py
sockoutlet/proxy/sandbox/storage.py
sockoutlet/utils/__init__.py
sockoutlet/utils/object_util.py
sockoutlet/utils/string_util.py
sockoutlet-0.0.2.dist-info/LICENSE.txt
sockoutlet-0.0.2.dist-info/METADATA
sockoutlet-0.0.2.dist-info/WHEEL
sockoutlet-0.0.2.dist-info/top_level.txt
sockoutlet-0.0.2.dist-info/RECORD
