Metadata-Version: 2.1
Name: sockoutlet
Version: 0.0.2
Summary: Public URLs for testing your chatbot
Home-page: https://github.com/skelethon/sockoutlet
Author: acegik
License: GPL-3.0
Download-URL: https://github.com/skelethon/sockoutlet/downloads
Keywords: proxy,tunnel,testing
Platform: UNKNOWN
Requires-Python: >=2.7,!=3.0.*,!=3.1.*,!=3.2.*,!=3.3.*
Requires-Dist: configator
Requires-Dist: proxy.py
